gridtree/__init__.py
gridtree/gridtree.py
gridtree-0.1.0.dist-info/LICENSE
gridtree-0.1.0.dist-info/WHEEL
gridtree-0.1.0.dist-info/METADATA
gridtree-0.1.0.dist-info/RECORD
