Metadata-Version: 2.1
Name: gridtree
Version: 0.1.0
Summary: Generalized quadtree.
Author: uigctaw
Author-email: uigctaw@protonmail.com
Requires-Python: >=3.9,<4.0
Classifier: Programming Language :: Python :: 3
Classifier: Programming Language :: Python :: 3.9
